MANIFEST.in
Makefile
README.md
setup.py
Demo/demo.py
Demo/demoLP.py
Demo/demoQP.py
Demo/demo_cutest.py
Demo/Data/A_dfl.npz
Demo/Data/A_qp.npz
Demo/Data/H_qp.npz
Demo/Data/bl_dfl.npy
Demo/Data/bl_qp.npy
Demo/Data/bu_dfl.npy
Demo/Data/bu_qp.npy
Demo/Data/c_dfl.npy
Demo/Data/c_qp.npy
Demo/Data/hi_dfl.npy
Demo/Data/hi_qp.npy
Demo/Data/lo_dfl.npy
Demo/Data/lo_qp.npy
SuiteOPT/Makefile
SuiteOPT.egg-info/PKG-INFO
SuiteOPT.egg-info/SOURCES.txt
SuiteOPT.egg-info/dependency_links.txt
SuiteOPT.egg-info/top_level.txt
SuiteOPT/CGDESCENT/Makefile
SuiteOPT/CGDESCENT/CUTEst/.cutest_location
SuiteOPT/CGDESCENT/CUTEst/.directoryname
SuiteOPT/CGDESCENT/CUTEst/.runcutest
SuiteOPT/CGDESCENT/CUTEst/Makefile
SuiteOPT/CGDESCENT/CUTEst/README
SuiteOPT/CGDESCENT/CUTEst/cg_descent
SuiteOPT/CGDESCENT/CUTEst/cg_descent_main.c
SuiteOPT/CGDESCENT/CUTEst/cg_install
SuiteOPT/CGDESCENT/CUTEst/classU
SuiteOPT/CGDESCENT/CUTEst/classUQP
SuiteOPT/CGDESCENT/CUTEst/gpl.txt
SuiteOPT/CGDESCENT/CUTEst/makemaster
SuiteOPT/CGDESCENT/CUTEst/runcutest
SuiteOPT/CGDESCENT/Demo/Makefile
SuiteOPT/CGDESCENT/Demo/gpl.txt
SuiteOPT/CGDESCENT/Demo/run_cg_descent.c
SuiteOPT/CGDESCENT/Demo/run_cg_descentQP.c
SuiteOPT/CGDESCENT/Include/cg_descent.h
SuiteOPT/CGDESCENT/Lib/Makefile
SuiteOPT/CGDESCENT/LibPy/Makefile
SuiteOPT/CGDESCENT/MATLAB/cg_descent_make.m
SuiteOPT/CGDESCENT/MATLAB/cg_descent_mex.c
SuiteOPT/CGDESCENT/MATLAB/demo.m
SuiteOPT/CGDESCENT/MATLAB/demoQP.m
SuiteOPT/CGDESCENT/MATLAB/gpl.txt
SuiteOPT/CGDESCENT/MATLAB/readme.m
SuiteOPT/CGDESCENT/Source/cg_default.c
SuiteOPT/CGDESCENT/Source/cg_descent.c
SuiteOPT/CGDESCENT/Source/cg_print.c
SuiteOPT/CGDESCENT/Source/cg_util.c
SuiteOPT/CGDESCENT/Source/gpl.txt
SuiteOPT/Doc/paper.tex
SuiteOPT/MATLAB/README
SuiteOPT/MATLAB/make.m
SuiteOPT/MATLAB/Include/cg_descent_matlab.h
SuiteOPT/MATLAB/Include/napheap_matlab.h
SuiteOPT/MATLAB/Include/pasa_matlab.h
SuiteOPT/MATLAB/Include/pproj_matlab.h
SuiteOPT/MATLAB/Include/suiteopt_matlab.h
SuiteOPT/MATLAB/Source/cg_descent_matlab.c
SuiteOPT/MATLAB/Source/napheap_matlab.c
SuiteOPT/MATLAB/Source/pasa_matlab.c
SuiteOPT/MATLAB/Source/pproj_matlab.c
